ignorelib.py
ignorelib-0.3.0.dist-info/LICENSE
ignorelib-0.3.0.dist-info/WHEEL
ignorelib-0.3.0.dist-info/METADATA
ignorelib-0.3.0.dist-info/RECORD
