Metadata-Version: 2.1
Name: ignorelib
Version: 0.3.0
Summary: Use the syntax and semantics of gitignore with custom ignore file names and locations
Home-page: https://github.com/benkehoe/ignorelib
License: Apache-2.0
Keywords: ignore,git,gitignore
Author: Ben Kehoe
Author-email: ben@kehoe.io
Requires-Python: >=3.5,<4.0
Classifier: Development Status :: 4 - Beta
Classifier: License :: OSI Approved :: Apache Software License
Classifier: Programming Language :: Python :: 3
Classifier: Programming Language :: Python :: 3.5
Classifier: Programming Language :: Python :: 3.6
Classifier: Programming Language :: Python :: 3.7
Classifier: Programming Language :: Python :: 3.8
Classifier: Topic :: Software Development :: Libraries
Classifier: Topic :: Software Development :: Libraries :: Python Modules
Classifier: Topic :: Software Development :: Version Control :: Git
Classifier: Topic :: System :: Filesystems
Project-URL: Repository, https://github.com/benkehoe/ignorelib
